odoo/addons/l10n_it_vat_registries_rc/README.rst
odoo/addons/l10n_it_vat_registries_rc/__init__.py
odoo/addons/l10n_it_vat_registries_rc/__manifest__.py
odoo/addons/l10n_it_vat_registries_rc/i18n/it.po
odoo/addons/l10n_it_vat_registries_rc/i18n/l10n_it_vat_registries_rc.pot
odoo/addons/l10n_it_vat_registries_rc/readme/CONTRIBUTORS.md
odoo/addons/l10n_it_vat_registries_rc/readme/DESCRIPTION.md
odoo/addons/l10n_it_vat_registries_rc/report/report_registro_iva.xml
odoo/addons/l10n_it_vat_registries_rc/static/description/icon.png
odoo/addons/l10n_it_vat_registries_rc/static/description/index.html
odoo_addon_l10n_it_vat_registries_rc-16.0.1.0.1.dist-info/METADATA
odoo_addon_l10n_it_vat_registries_rc-16.0.1.0.1.dist-info/WHEEL
odoo_addon_l10n_it_vat_registries_rc-16.0.1.0.1.dist-info/top_level.txt
odoo_addon_l10n_it_vat_registries_rc-16.0.1.0.1.dist-info/RECORD
